cloudbandpy/__init__.py
cloudbandpy/cb_detection.py
cloudbandpy/cloudband.py
cloudbandpy/figure_tools.py
cloudbandpy/io_utilities.py
cloudbandpy/load_driver.py
cloudbandpy/misc.py
cloudbandpy/time_utilities.py
cloudbandpy/tracking.py
cloudbandpy-1.2.2.dist-info/LICENSE.txt
cloudbandpy-1.2.2.dist-info/METADATA
cloudbandpy-1.2.2.dist-info/WHEEL
cloudbandpy-1.2.2.dist-info/top_level.txt
cloudbandpy-1.2.2.dist-info/RECORD
