Metadata-Version: 2.2
Name: cloudbandpy
Version: 1.2.2
Summary: A Python package for atmospheric cloud bands detection.
Home-page: https://github.com/romainpilon/cloudbandpy
Author: Romain Pilon
Author-email: romain.pilon@gmail.com
Classifier: Programming Language :: Python :: 3
Classifier: License :: OSI Approved :: BSD License
Classifier: Operating System :: OS Independent
Classifier: Topic :: Scientific/Engineering :: Atmospheric Science
License-File: LICENSE.txt
Requires-Dist: numpy>=1.23.5
Requires-Dist: netcdf4>=1.6.2
Requires-Dist: pandas>=1.5
Requires-Dist: pyyaml>=6.0
Requires-Dist: scikit-image>=0.19.2
Requires-Dist: colorcet>=3.0
Requires-Dist: metpy>=1.4.0
Requires-Dist: proj
Requires-Dist: cartopy>=0.21.1
